vistir/__init__.py
vistir/_winconsole.py
vistir/cmdparse.py
vistir/contextmanagers.py
vistir/cursor.py
vistir/misc.py
vistir/path.py
vistir/spin.py
vistir/termcolors.py
vistir-0.8.0.dist-info/LICENSE
vistir-0.8.0.dist-info/METADATA
vistir-0.8.0.dist-info/WHEEL
vistir-0.8.0.dist-info/top_level.txt
vistir-0.8.0.dist-info/zip-safe
vistir-0.8.0.dist-info/RECORD
