Metadata-Version: 2.1
Name: vistir
Version: 0.8.0
Summary: Miscellaneous utilities for dealing with filesystems, paths, projects, subprocesses, and more.
Home-page: https://github.com/sarugaku/vistir
Author: Dan Ryan
Author-email: dan@danryan.co
License: ISC License
Keywords: tools,utilities,backports,paths,subprocess,filesystem
Classifier: Development Status :: 4 - Beta
Classifier: License :: OSI Approved :: ISC License (ISCL)
Classifier: Programming Language :: Python :: 3
Classifier: Programming Language :: Python :: 3.7
Classifier: Programming Language :: Python :: 3.8
Classifier: Programming Language :: Python :: 3.9
Classifier: Programming Language :: Python :: 3.10
Classifier: Topic :: Software Development :: Libraries :: Python Modules
Requires-Python: >=3.7
Provides-Extra: requests
Provides-Extra: dev
Provides-Extra: tests
Provides-Extra: typing
License-File: LICENSE
